ilsmc/__init__.py
ilsmc/combine_states.py
ilsmc/cutpoints.py
ilsmc/get_ABC.py
ilsmc/get_joint_prob_mat.py
ilsmc/get_ordered.py
ilsmc/get_tab.py
ilsmc/get_times.py
ilsmc/load_trans_mat.py
ilsmc/vanloan.py
ilsmc/data/trans_mat_full_1.csv
ilsmc/data/trans_mat_full_2.csv
ilsmc/data/trans_mat_full_3.csv
ilsmc_rivasiker-0.0.6.dist-info/LICENSE
ilsmc_rivasiker-0.0.6.dist-info/METADATA
ilsmc_rivasiker-0.0.6.dist-info/WHEEL
ilsmc_rivasiker-0.0.6.dist-info/top_level.txt
ilsmc_rivasiker-0.0.6.dist-info/RECORD
