Metadata-Version: 2.1
Name: ilsmc-rivasiker
Version: 0.0.6
Summary: A phylogenetically aware SMC to infer the evolutionary history of species
Home-page: https://github.com/rivasiker/ilsmc
Author: Iker Rivas-González
Author-email: irg@birc.au.dk
License: UNKNOWN
Project-URL: Bug Tracker, https://github.com/rivasiker/ilsmc/issues
Platform: UNKNOWN
Classifier: Programming Language :: Python :: 3
Classifier: License :: OSI Approved :: MIT License
Classifier: Operating System :: OS Independent
Requires-Python: >=3.6
License-File: LICENSE
Requires-Dist: numpy
Requires-Dist: pandas
Requires-Dist: scipy
Requires-Dist: multiprocess
